.gitignore
CHANGELOG.md
LICENSE.txt
MANIFEST.in
README.md
__init__.py
examples.md
multicolorfits.py
readthedocs.yml
readthedocs_v1.yml
setup.py
docs/Makefile
docs/source/changelog.rst
docs/source/conf.py
docs/source/examples.rst
docs/source/index.rst
docs/source/multicolorfits.rst
docs/source/reference_api.rst
docs/source/requirements.txt
docs/source/rtd-environment.yml
examples/ngc602.md
examples/wlm.md
multicolorfits.egg-info/PKG-INFO
multicolorfits.egg-info/SOURCES.txt
multicolorfits.egg-info/dependency_links.txt
multicolorfits.egg-info/requires.txt
multicolorfits.egg-info/top_level.txt