Metadata-Version: 2.1
Name: multicolorfits
Version: 2.1.3
Summary: GUI tool to colorize and combine multiple fits images for making visually aesthetic scientific plots
Home-page: https://github.com/pjcigan/multicolorfits
Author: Phil Cigan
Author-email: 
License: MIT
License-File: LICENSE.txt
Requires-Dist: numpy
Requires-Dist: matplotlib
Requires-Dist: astropy
Requires-Dist: scipy
Requires-Dist: pyface
Requires-Dist: traits
Requires-Dist: traitsui
Requires-Dist: scikit-image
Requires-Dist: pyqt4; python_version < "3"
Requires-Dist: pyqt5; python_version < "3.7"
Requires-Dist: pyqt6; python_version >= "3.7"
Provides-Extra: reproject
Requires-Dist: reproject; extra == "reproject"
